apiautomata/API.py
apiautomata/__init__.py
apiautomata/__main__.py
apiautomata/holder/ItemHolder.py
apiautomata/holder/Items.py
apiautomata/holder/__init__.py
apiautomata/process/ProcessInvoker.py
apiautomata/process/__init__.py
apiautomata/proxify/Proxify.py
apiautomata/proxify/__init__.py
apiautomata/routes/__init__.py
apiautomata/routes/home.py
apiautomata/routes/proxy.py
apiautomata/routes/exchange/__init__.py
apiautomata/routes/exchange/exchange_rate.py
apiautomata/routes/exchange/instrument_exchange.py
apiautomata/routes/missing/__init__.py
apiautomata/routes/missing/missing.py
apiautomata/routes/process/__init__.py
apiautomata/routes/process/process_enablement.py
apiautomata/routes/process/process_invoke.py
apiautomata/routes/process/process_status.py
apiautomata/routes/transform/__init__.py
apiautomata/routes/transform/exchange_transform.py
apiautomata/routes/transform/trade_transform.py
apiautomata/server/AutomataAPIServer.py
apiautomata/server/__init__.py
persuader_technology_automata_api-0.2.2.dist-info/LICENSE
persuader_technology_automata_api-0.2.2.dist-info/METADATA
persuader_technology_automata_api-0.2.2.dist-info/WHEEL
persuader_technology_automata_api-0.2.2.dist-info/entry_points.txt
persuader_technology_automata_api-0.2.2.dist-info/top_level.txt
persuader_technology_automata_api-0.2.2.dist-info/RECORD
