Metadata-Version: 2.1
Name: persuader-technology-automata-api
Version: 0.2.2
Summary: Automata API
Author: Persuader Technology
Author-email: software@persuader.technology
License: UNLICENSE
Classifier: Programming Language :: Python :: 3
License-File: LICENSE
Requires-Dist: fastapi (==0.78.0)
Requires-Dist: uvicorn (==0.17.6)
Requires-Dist: aiohttp (==3.8.1)
Requires-Dist: persuader-technology-automata-core (>=0.5.7)
Requires-Dist: persuader-technology-automata-utilities (>=0.1.3)
Requires-Dist: persuader-technology-automata-logger (>=0.0.4)
Requires-Dist: persuader-technology-automata-redis (>=0.3.5)
Requires-Dist: persuader-technology-automata-missing-repository (>=0.1.8)
Requires-Dist: persuader-technology-automata-exchange-repository (>=0.2.8)
Requires-Dist: persuader-technology-automata-exchange-transform-repository (>=0.1.8)
Requires-Dist: persuader-technology-automata-trade-transform-repository (>=0.1.0)
Requires-Dist: persuader-technology-automata-process-repository (>=0.1.9)
